{
  "chunk_content": "### Перечень и мощность энергопринимающих устройств.\n\nПеречень и мощность ЭПУ можно оформить по форме либо составить список от руки. Итоговая мощность в перечне ЭПУ, не должна превышать мощности, указанной в заявке!\n## Перечень и мощность энергопринимающих устройств\n\nИванов Иван Иванович\n*(ФИО заявителя)*\n\n<table>\n    <tr>\n        <th>№</th>\n        <th>Наименование энергопринимающего устройства</th>\n        <th>Мощность, кВт</th>\n    </tr>\n<tr>\n        <td>1.</td>\n<td>Освещение</td>\n    </tr>\n<tr>\n        <td>2.</td>\n<td>Бытовые приборы</td>\n    </tr>\n<tr>\n        <td>3.</td>\n<td>Электроинструменты</td>\n    </tr>\n<tr>\n        <td>4.</td>\n<td>ИТОГО</td>\n    </tr>\n<tr>\n        <td>5.</td>\n<td></td>\n    </tr>\n<tr>\n        <td>6.</td>\n<td></td>\n    </tr>\n<tr>\n        <td>7.</td>\n<td></td>\n    </tr>\n<tr>\n        <td>8.</td>\n<td></td>\n    </tr>\n<tr>\n        <td>9.</td>\n<td></td>\n    </tr>\n<tr>\n        <td>10.</td>\n<td></td>\n    </tr>\n<tr>\n        <td>11.</td>\n<td></td>\n    </tr>\n<tr>\n        <td>12.</td>\n<td></td>\n    </tr>\n<tr>\n        <td>13.</td>\n<td></td>\n    </tr>\n</table>\n\nПосле того как все документы прикреплены, необходимо нажать кнопку «Отправить». После будет выдано сообщение «Заявка отправлена».\n\nПосле этого заявка на ТП поступает на обработку специалистам по ТП ООО «Башкирэнерго».\n\n### Этапы обработки заявки/обращения. Обмен электронными документами\nОбщие сведения об этапах ТП\n\nВ зависимости от вида созданной заявки/обращения, а также от требуемых параметров ТП, состав этапов (и сроки их выполнения), которые она пройдет от регистрации до выполнения, может значительно отличаться. Также некоторые этапы должны быть всегда (например, регистрация заявки), а некоторые – только при определенных условиях (например, прием недостающих документов или допуска РТН).\n\nНа некоторых этапах ТП может приостанавливаться до выполнения каких-то действий заявителем, например, отправки каких-то дополнительных документов или оплаты договора на ТП.\n\nДля заявки на ТП основные этапы следующие:\n\n* Регистрация заявки;\n\n* Подготовка ТУ и проекта договора на ТП;\n\n* Заключение договора на ТП;\n\n* Выполнение мероприятий по ТУ;\n\n28\n- Непосредственное осуществление ТП.\n\nДля других видов они другие.\n\nСхематично посмотреть, на каком этапе находится поданная заявка, можно, раскрыв пункт «Текущее состояние» для этой заявки:",
  "breadcrumbs": "Инструкция > Подача заявки > Этапы обработки",
  "chunk_summary": "Описание перечня энергопринимающих устройств и этапов обработки заявки на ТП.",
  "hypothetical_questions": [
    "Как оформить перечень энергопринимающих устройств?",
    "Какие этапы проходит заявка на ТП?",
    "Как посмотреть текущее состояние заявки?"
  ],
  "keywords": [
    "энергопринимающие устройства",
    "этапы обработки",
    "регистрация заявки",
    "ТУ",
    "договор на ТП",
    "ТП",
    "отправка заявки"
  ],
  "category": "ТПП",
  "collection_name": "operational_content",
  "document_type": "stage_description",
  "power_range": "any",
  "client_type": "any",
  "chunk_id": "0a38dc52a0c6_p12",
  "source_file": "10. Инструкция по работе в ЛК (для заявителя) (от января 2024)"
}