{
  "chunk_content": "# СОСТАВ, ПОСЛЕДОВАТЕЛЬНОСТЬ И СРОКИ ОКАЗАНИЯ УСЛУГИ (ПРОЦЕССА):\n\n<table>\n  <thead>\n    <tr>\n        <th>№</th>\n        <th>Этап</th>\n        <th>Содержание /условие</th>\n        <th>Форма предоставления</th>\n        <th>Срок исполнения</th>\n        <th>Ссылка на нормативный правовой акт</th>\n    </tr>\n  </thead>\n  <tbody>\n    <tr>\n        <td>1</td>\n<td>Подача заявки на технологическое присоединение.</td>\n<td>1.1. Заявитель подает заявку на технологическое присоединение.<br/>В случае технологического присоединения объектов микрогенерации заявка на технологическое присоединение подается в сетевую организацию, к объектам электросетевого хозяйства которой технологически присоединены принадлежащие заявителю энергопринимающие устройства потребителя электрической энергии. В случае одновременного технологического присоединения объектов микрогенерации и энергопринимающих устройств потребителя электрической энергии, которому принадлежат на праве собственности или на ином законном основании такие объекты микрогенерации, заявка на технологическое присоединение подается в сетевую организацию, определенную в соответствии с пунктом 8 Правил, с учетом особенностей, установленных пунктом 8(5) Правил.<br/>В случае если в соответствии с Правилами в целях технологического присоединения предусматриваются разработка и согласование схемы выдачи мощности объекта по производству электрической энергии (далее - схема выдачи мощности) или схемы внешнего электроснабжения энергопринимающего устройства (далее - схема внешнего электроснабжения), заявка подается в сетевую организацию, определенную в соответствии с рекомендуемым вариантом прилагаемой к заявке схемы выдачи мощности или схемы внешнего электроснабжения.</td>\n<td>Обращение заявителя (уполномоченного представителя) с заявкой в:<br/>- очно ЦОК /ОПП¹;<br/>-в электронной форме через «Личный кабинет потребителя услуг по технологическому присоединению» на официальном сайте ООО «Башкирэнерго» в сети «Интернет» http://www.bashkirenergo.ru/ (либо посредством переадресации на официальный сайт, обеспечивающий возможность направлять заявку и прилагаемые документы);<br/>- по почте.</td>\n<td>Не ограничен.</td>\n<td>Пункты 8-10, 12(1) Правил ²</td>\n    </tr>\n  </tbody>\n<tr>\n        <td> </td>\n<td> </td>\n<td>энергии (далее - схема выдачи мощности) или схемы внешнего электроснабжения энергопринимающего устройства (далее - схема внешнего электроснабжения), заявка подается в сетевую организацию, определенную в соответствии с рекомендуемым вариантом прилагаемой к заявке схемы выдачи мощности или схемы внешнего электроснабжения.</td>\n<td> </td>\n<td> </td>\n<td> </td>\n    </tr>\n<tr>\n        <td> </td>\n<td> </td>\n<td>1.2. В случае наличия у заявителя договора, обеспечивающего продажу электрической энергии (мощности) на розничном рынке, в рамках которого заявителем предполагается осуществление энергоснабжения энергопринимающих устройств, в отношении которых подается заявка, в заявке указываются наименование субъекта розничного рынка, номер и дата указанного договора с приложением документов, подтверждающих полномочия представителя заявителя на заключение такого договора.<br/>По желанию заявителя, при его намерении заключить договор энергоснабжения (купли-продажи (поставки) электрической энергии (мощности) с гарантирующим поставщиком, к заявке прилагается</td>\n<td>По желанию заявителя заполняется соответствующий раздел заявки с приложением документов, предусмотренных п.34 Основных положений.<br/>В случае подачи заявки очно или почтой – представляется заполненное согласие на обработку персональных данных сетевой организацией и субъектом розничного рынка, с которым заявитель намеревается заключить договор, обеспечивающий продажу электрической энергии (мощности) на розничном рынке.</td>\n<td>До завершения процедуры технологического присоединения</td>\n<td>Пункт 8, подпункт «л» пункта 9 Правил, Пункты 33, 34 Основных положений<sup>3</sup></td>\n    </tr>\n  </table>",
  "breadcrumbs": "Состав, последовательность и сроки > Этап 1 > Подача заявки",
  "chunk_summary": "Описание первого этапа технологического присоединения: подача заявки. Включает способы подачи (очно, онлайн, почта), особенности для микрогенерации и требования к договору энергоснабжения.",
  "hypothetical_questions": [
    "Как подать заявку на технологическое присоединение онлайн?",
    "Нужен ли договор энергоснабжения при подаче заявки?",
    "Куда подавать заявку на ТП объектов микрогенерации?",
    "Какие документы нужны для подачи заявки?"
  ],
  "keywords": [
    "подача заявки",
    "технологическое присоединение",
    "Личный кабинет",
    "микрогенерация",
    "ЦОК",
    "ОПП",
    "договор энергоснабжения",
    "ООО «Башкирэнерго»",
    "Правила №861"
  ],
  "category": "ТПП",
  "collection_name": "operational_content",
  "document_type": "stage_description",
  "power_range": "150-670kW",
  "client_type": "any",
  "chunk_id": "52ebc6228555_p2",
  "source_file": "passport-tp-150-670kvt"
}