{
  "chunk_content": "## Заключение договора\n\nИнформацию о готовности проекта договора на осуществление технологического присоединения и технические условия можно получить:\n\n- [через «Личный кабинет потребителя услуг по технологическому присоединению»](https://www.bashkirenergo.ru/personal/docs.php) на [официальном сайте ООО «Башкирэнерго»](https://www.bashkirenergo.ru/) в сети «Интернет»\n- [в Центре обслуживания клиентов](../map/?target=2914#contact-block)\n- [в пунктах обслуживания потребителей ООО «Башкирэнерго»](../map/?target=2853#contact-block)\n- через СМС-сообщение (при выборе данной услуги в заявке)\n\nЗаполненный и подписанный сетевой организацией проект договора на осуществление технологического присоединения\n(в двух экземплярах) и технические условия к нему можно получить:\n\n- [в Центре обслуживания клиентов](../map/?target=2914#contact-block)\n- [в пунктах обслуживания потребителей ООО «Башкирэнерго»](../map/?target=2853#contact-block)\n- в почтовом отделении (при выборе данной услуги в\nзаявке)\n\nПосле получения проекта договора на осуществление технологического присоединения и технических условий к нему заявителю необходимо:\n\n- ознакомиться с проектом договора и технических условий\n- подписать оба экземпляра проекта договора в течение 10 дней с даты получения подписанного ООО «Башкирэнерго» проекта договора\n- вернуть в ООО «Башкирэнерго» в указанный срок один экземпляр подписанного договора с приложением к нему документов, подтверждающих полномочия лица, подписавшего такой договор, либо, в случае несогласия с представленным проектом договора, направить в ООО «Башкирэнерго» мотивированный отказ от подписания проекта договора с предложением об изменении представленного проекта договора\n- произвести оплату по реквизитам, указанным в договоре\n\nДоговор считается заключенным с даты поступления\nподписанного заявителем экземпляра договора в\nсетевую организацию\nВ случае ненаправления заявителем подписанного проекта\ndogovora либо мотивированного отказа от его подписания, но не\nранее чем через 30 рабочих дней со дня получения заявителем\nподписанного сетевой организацией проекта договора и\ntехнических условий, поданная этим заявителем заявка\nаннулируется.\n\n**Формы договоров на технологическое присоединение**\n\n[Формы договоров на технологическое присоединение](#zayavka__zakl_dogovor)\n\n## Формы договоров на технологическое присоединение для физических лиц\n\n- [Типовой договор об осуществлении технологического присоединения к электрическим сетям (для юридических лиц или индивидуальных предпринимателей в целях технологического присоединения энергопринимающих устройств, максимальная мощность которых свыше 150 кВт и менее 670 кВт) с техническими условиями](https://www.bashkirenergo.ru/?get-file-by-id=3389)\n- [Типовой договор об осуществлении технологического присоединения к электрическим сетям посредством перераспределения максимальной мощности (для заявителей, заключивших соглашение о перераспределении максимальной мощности с владельцами энергопринимающих устройств с техническими условиями](https://www.bashkirenergo.ru/?get-file-by-id=3390)\n- [Соглашение о перераспределении максимальной мощности (с уведомлением)](https://www.bashkirenergo.ru/?get-file-by-id=3367)\n- [Соглашение об уменьшении максимальной мощности энергопринимающих устройств](https://www.bashkirenergo.ru/?get-file-by-id=3368)\n\n## Формы договоров на технологическое присоединение для юридических лиц и индивидуальных предпринимателей\n\n- [Типовой договор об осуществлении технологического присоединения к электрическим сетям (для юридических лиц или индивидуальных предпринимателей в целях технологического присоединения энергопринимающих устройств, максимальная мощность которых свыше 150 кВт и менее 670 кВт) с техническими условиями](https://www.bashkirenergo.ru/?get-file-by-id=3391)\n- [Типовой договор об осуществлении технологического присоединения к электрическим сетям посредством перераспределения максимальной мощности (для заявителей, заключивших соглашение о перераспределении максимальной мощности с владельцами энергопринимающих устройств с техническими условиями](https://www.bashkirenergo.ru/?get-file-by-id=3392)\n- [Соглашение о перераспределении максимальной мощности (с уведомлением)](https://www.bashkirenergo.ru/?get-file-by-id=3367)\n- [Соглашение об уменьшении максимальной мощности энергопринимающих устройств](https://www.bashkirenergo.ru/?get-file-by-id=3368)\n\nСтоимость платы за технологическое присоединение\nрассчитывается исходя из [установленных ставок платы для ООО\n«Башкирэнерго» на текущий период регулирования](https://www.bashkirenergo.ru/?get-file-by-id=3325)Рассчитать ориентировочную стоимость платы за\ntехнологическое присоединение можно с использованием\n[онлайн-калькулятора](../calc/)",
  "breadcrumbs": "Технологическое присоединение свыше 670 кВт > Заключение договора",
  "chunk_summary": "Описан процесс заключения договора на технологическое присоединение: получение проекта, сроки подписания, оплата и условия аннулирования заявки. Приведены ссылки на типовые формы договоров для физических и юридических лиц, а также информация о расчете стоимости ТП.",
  "hypothetical_questions": [
    "Сколько дней на подписание договора ТП?",
    "Что делать, если не согласен с проектом договора?",
    "Как рассчитать стоимость технологического присоединения?",
    "Когда аннулируется заявка на ТП?",
    "Где скачать типовой договор об осуществлении ТП?"
  ],
  "keywords": [
    "заключение договора",
    "проект договора",
    "технические условия",
    "оплата ТП",
    "аннулирование заявки",
    "10 дней",
    "30 рабочих дней",
    "онлайн-калькулятор",
    "ставки платы",
    "ООО «Башкирэнерго»"
  ],
  "category": "ТПП",
  "collection_name": "operational_content",
  "document_type": "stage_description",
  "power_range": ">670kW",
  "client_type": "any",
  "chunk_id": "a9293559774f_p3",
  "source_file": "tp-svyshe-670kvt"
}