{
  "chunk_content": "4. Государственному регулированию на оптовом и (или) на розничных рынках подлежат:\n*   цены (тарифы) на услуги по обеспечению системной надежности (в случаях, предусмотренных законодательством Российской Федерации, в порядке, установленном Правительством Российской Федерации);\n*   цены (тарифы) на услуги коммерческого оператора;\n*   цены (тарифы) на услуги по оперативно-диспетчерскому управлению в электроэнергетике в части управления технологическими режимами работы объектов электроэнергетики и энергопринимающих устройств потребителей электрической энергии, обеспечения функционирования технологической инфраструктуры оптового и розничных рынков и осуществления проектирования развития электроэнергетических систем;\n*   предельные (минимальный и (или) максимальный) уровни цен (тарифов) на услуги по передаче электрической энергии по электрическим сетям, принадлежащим на праве собственности или ином законном основании территориальным сетевым организациям.",
  "breadcrumbs": "Статья 23.1. Государственное регулирование цен (тарифов) на оптовом и розничных рынках",
  "chunk_summary": "Указываются услуги, подлежащие регулированию на обоих типах рынков: системная надежность, услуги коммерческого оператора, оперативно-диспетчерское управление и услуги по передаче электроэнергии.",
  "hypothetical_questions": [
    "Какие услуги подлежат регулированию на оптовом и розничном рынках?",
    "Как регулируются тарифы на услуги по передаче электроэнергии?",
    "Подлежат ли регулированию услуги коммерческого оператора?",
    "Какие тарифы устанавливаются на услуги по обеспечению системной надежности?",
    "Как регулируются услуги оперативно-диспетчерского управления?"
  ],
  "keywords": [
    "услуги",
    "системная надежность",
    "коммерческий оператор",
    "оперативно-диспетчерское управление",
    "передача электроэнергии",
    "территориальные сетевые организации"
  ],
  "entities": [
    "Правительство Российской Федерации",
    "коммерческий оператор",
    "территориальные сетевые организации",
    "Единая энергетическая система России"
  ],
  "chunk_id": "081b2d80fe26_p4",
  "source_file": "1. ФЗ 35 (28.04.2025).md",
  "category": "legal"
}