{
  "chunk_content": "**Важно:** Потребители электрической энергии, энергоснабжение ЭПУ которых осуществляется по III категории надежности электроснабжения, не вправе перераспределять свою максимальную мощность в пользу потребителей, энергоснабжение ЭПУ которых осуществляется по I и II категориям надежности электроснабжения.\nТакже не допускается снижение объема максимальной мощности собственных ЭПУ с одновременным перераспределением объема снижения максимальной мощности лица, осуществившего технологическое присоединение ЭПУ, объектов электросетевого хозяйства, в пользу собственника или иного законного владельца объекта по производству электрической энергии.",
  "breadcrumbs": "Особенности технологического присоединения > Перераспределение максимальной мощности > Ограничения",
  "chunk_summary": "Описаны важные ограничения: запрет на перераспределение мощности от III категории к I и II, а также запрет на перераспределение в пользу производителей электроэнергии.",
  "hypothetical_questions": [
    "Можно ли перераспределять мощность с III категории на I?",
    "Можно ли перераспределять мощность в пользу производителя электроэнергии?",
    "Какие ограничения существуют для перераспределения мощности?",
    "Можно ли снизить мощность собственных ЭПУ и передать ее производителю?"
  ],
  "keywords": [
    "ограничения",
    "категория надежности",
    "производитель электроэнергии",
    "запрет",
    "перераспределение"
  ],
  "entities": [
    "I категория надежности",
    "II категория надежности",
    "III категория надежности",
    "объекты электросетевого хозяйства"
  ],
  "chunk_id": "ba8fd93f187f_p6",
  "source_file": "22.Документ из сайта, особенности тех приса.md",
  "category": "informational"
}