{
  "chunk_content": "## VII. Особенности временного технологического присоединения\n(в ред. Постановления Правительства РФ от 26.08.2013 N 737)\n\n**50.** Временным технологическим присоединением является технологическое присоединение энергопринимающих устройств по третьей категории надежности электроснабжения на уровне напряжения ниже 35 кВ, осуществляемое на ограниченный период времени для обеспечения электроснабжения энергопринимающих устройств.\n\nВременное технологическое присоединение, а также заключение и исполнение договоров об осуществлении временного технологического присоединения, на основании которых оно производится, осуществляется в соответствии с предусмотренным настоящими Правилами общим порядком технологического присоединения с учетом особенностей, установленных в настоящем разделе.",
  "breadcrumbs": "VII. Особенности временного технологического присоединения > Пункт 50",
  "chunk_summary": "Пункт определяет понятие временного технологического присоединения: подключение устройств 3-й категории надежности, напряжение ниже 35 кВ, ограниченный срок. Процедура осуществляется по общим правилам с учетом особенностей раздела.",
  "hypothetical_questions": [
    "Что такое временное технологическое присоединение?",
    "Для каких объектов допускается временное присоединение?",
    "Какой класс напряжения применяется для временного присоединения?",
    "По каким правилам заключается договор на временное присоединение?"
  ],
  "keywords": [
    "временное технологическое присоединение",
    "надежность электроснабжения",
    "напряжение",
    "договор",
    "энергопринимающие устройства"
  ],
  "entities": [
    "Постановление Правительства РФ от 26.08.2013 N 737",
    "третья категория надежности электроснабжения",
    "35 кВ"
  ],
  "chunk_id": "d4c891d02f66_p5",
  "source_file": "2. 861 (28.04.2025).md",
  "category": "legal"
}