{
  "chunk_content": "### 31. При отсутствии нормативов по отдельным статьям расходов допускается использование в расчетах экспертных оценок, основанных на отчетных данных, представляемых организацией, осуществляющей регулируемую деятельность.",
  "breadcrumbs": "Основы ценообразования > 31. Экспертные оценки",
  "chunk_summary": "Устанавливает возможность использования экспертных оценок при расчете расходов, если отсутствуют нормативы по отдельным статьям. Оценки базируются на отчетных данных организации.",
  "hypothetical_questions": [
    "Что делать, если отсутствуют нормативы по статьям расходов?",
    "На чем основываются экспертные оценки?",
    "Кто предоставляет отчетные данные для экспертных оценок?",
    "Допускается ли использование экспертных оценок в расчетах?"
  ],
  "keywords": [
    "нормативы",
    "экспертные оценки",
    "отчетные данные",
    "расчеты",
    "регулируемая деятельность"
  ],
  "entities": [
    "регулирующий орган",
    "организация"
  ],
  "chunk_id": "483041665e5c_p5",
  "source_file": "3. 1178 Основы ценообразования.md",
  "category": "legal"
}