{
  "chunk_content": "## II. Организация очного обслуживания\n\n11. Положения настоящей главы об организации центральных офисов обслуживания потребителей и организации обслуживания в таких офисах распространяются на территориальные сетевые организации.",
  "breadcrumbs": "II. Организация очного обслуживания",
  "chunk_summary": "Данный фрагмент устанавливает сферу применения положений главы об организации офисов обслуживания потребителей, распространяя их на территориальные сетевые организации.",
  "hypothetical_questions": [
    "На какие организации распространяются положения об организации офисов обслуживания потребителей?",
    "Что регулирует глава II Единых стандартов обслуживания?",
    "Кто является субъектом организации центральных офисов обслуживания?",
    "Распространяются ли правила на территориальные сетевые организации?"
  ],
  "keywords": [
    "территориальные сетевые организации",
    "офисы обслуживания потребителей",
    "глава II",
    "Единые стандарты",
    "организация обслуживания"
  ],
  "entities": [
    "территориальные сетевые организации",
    "офисы обслуживания потребителей",
    "Единые стандарты"
  ],
  "chunk_id": "7834e068c5b8_p1",
  "source_file": "8. 186 О единых стандартах обслуживания.md",
  "category": "legal"
}