{
  "chunk_content": "**144.** Энергопринимающие устройства потребителя, объекты по производству электрической энергии (мощности) производителя электрической энергии (мощности) на розничном рынке считаются оборудованными приборами учета, позволяющими измерять почасовые объемы потребления (производства) электрической энергии, в случае если такими приборами учета оборудованы все точки поставки в границах балансовой принадлежности потребителя, производителя электрической энергии (мощности) на розничном рынке, кроме тех точек поставки, по которым в соответствии с настоящим пунктом допускается использование интегральных приборов учета.\nИспользование интегральных приборов учета допускается по точкам поставки на объектах электросетевого хозяйства напряжением 10 кВ и ниже при условии, что суммарная максимальная мощность по этим точкам поставки не превышает 2,5 процента максимальной мощности всех точек поставки в границах балансовой принадлежности потребителя. В этом случае при формировании почасовых объемов потребления электрической энергии учет объемов потребления электрической энергии по точкам поставки, оборудованным интегральными приборами учета, производится следующим образом. Суммарный объем потребления электрической энергии за расчетный период по точкам поставки, оборудованным интегральными приборами учета, распределяется по часам расчетного периода пропорционально доле объема потребления электрической энергии за каждый час расчетного периода, определенного суммарно по всем точкам поставки, оборудованным приборами учета, позволяющими измерять почасовые объемы потребления электрической энергии, в суммарном объеме потребления электрической энергии за расчетный период по всем точкам поставки, оборудованным приборами учета, позволяющими измерять почасовые объемы потребления электрической энергии. Указанные точки (группы точек) поставки, с использованием которых осуществляется торговля электрической энергией и мощностью на оптовом рынке, должны быть оборудованы средствами измерений в соответствии с требованиями, установленными Правилами оптового рынка. Использование показаний интегральных приборов учета для целей подтверждения выполнения обязательств по договорам оказания услуг по изменению режима потребления электрической энергии, заключенных потребителями электрической энергии розничных рынков, не допускается.",
  "breadcrumbs": "9. 442 О ФУНКЦИОНИРОВАНИИ РОЗНИЧНЫХ РЫНКОВ.md > Пункт 144",
  "chunk_summary": "Устанавливаются требования к измерению почасовых объемов и условия использования интегральных приборов учета, включая порядок распределения объемов.",
  "hypothetical_questions": [
    "Когда энергопринимающие устройства считаются оборудованными приборами учета почасовых объемов?",
    "Когда допускается использование интегральных приборов?",
    "Как распределяются объемы при использовании интегральных приборов?",
    "Можно ли использовать интегральные приборы для изменения режима?"
  ],
  "keywords": [
    "почасовые объемы",
    "интегральный прибор учета",
    "10 кВ",
    "2,5 процента",
    "оптовый рынок",
    "изменение режима"
  ],
  "entities": [
    "оптовый рынок",
    "Правила оптового рынка",
    "договоры оказания услуг",
    "электросетевое хозяйство"
  ],
  "chunk_id": "8a6d5fe4fbc0_p9",
  "source_file": "9. 442 О ФУНКЦИОНИРОВАНИИ РОЗНИЧНЫХ РЫНКОВ.md",
  "category": "legal"
}