{
  "chunk_content": "**171.** Сетевая организация уведомляет ежемесячно, до 25-го числа текущего месяца, гарантирующего поставщика (энергосбытовую, энергоснабжающую организацию) о включенных в разработанный ею план-график проведения проверок расчетных приборов учета на следующий месяц точках поставки потребителей (производителей электрической энергии (мощности) на розничных рынках), обслуживание которых осуществляет такой гарантирующий поставщик (энергосбытовая, энергоснабжающая организация) и которые расположены в границах объектов электросетевого хозяйства сетевой организации, способом, позволяющим подтвердить факт получения уведомления.\n\nГарантирующий поставщик уведомляет ежемесячно, до 25-го числа текущего месяца, сетевую организацию о включенных в разработанный ею план-график проведения проверок коллективных (общедомовых) расчетных приборов учета на следующий месяц точках поставки многоквартирных домов, которые непосредственно (опосредованно) присоединены к объектам электросетевого хозяйства сетевой организации.\n\nВ плане-графике проведения проверок расчетных приборов учета должны быть указаны точки поставки электрической энергии, в отношении которых проводится проверка, дата и время проведения проверки с учетом режима работы объекта и форма проверки.\n\nГарантирующий поставщик (энергосбытовая, энергоснабжающая организация, сетевая организация) в течение 2 рабочих дней обязан направить сетевой организации (гарантирующему поставщику, энергосбытовой, энергоснабжающей организации) ответ, содержащий:\n- согласие с планом-графиком проведения проверок расчетных приборов учета либо предложение об изменении состава планируемых к проверке точек поставки, но не более чем на 20 процентов точек поставки, планируемых к проверке в соответствии с этим планом-графиком, а также перечень точек поставки из числа точек поставки, согласованных для включения в указанный план-график для проведения инструментальной проверки;\n- перечень точек поставки, при проведении проверки в отношении которых планируется участие представителей гарантирующего поставщика (энергосбытовой, энергоснабжающей организации, сетевой организации).",
  "breadcrumbs": "Правила функционирования розничных рынков > Пункт 171",
  "chunk_summary": "Регламентируется порядок обмена информацией о планах-графиках проверок приборов учета между сетевыми организациями и гарантирующими поставщиками. Устанавливаются сроки уведомления (до 25 числа) и порядок согласования точек поставки.",
  "hypothetical_questions": [
    "Когда сетевая организация должна уведомить поставщика о плане проверок?",
    "Какие данные должны содержаться в плане-графике проверок?",
    "В какой срок гарантирующий поставщик должен ответить на план проверок?",
    "Можно ли изменить состав точек поставки в плане проверок?",
    "Каким способом должно быть подтверждено получение уведомления о проверках?"
  ],
  "keywords": [
    "план-график проверок",
    "сетевая организация",
    "гарантирующий поставщик",
    "уведомление",
    "точки поставки",
    "согласование",
    "расчетные приборы учета"
  ],
  "entities": [
    "сетевая организация",
    "гарантирующий поставщик",
    "энергосбытовая организация",
    "25-е число",
    "2 рабочих дня",
    "20 процентов"
  ],
  "chunk_id": "77dd90502b0b_p2",
  "source_file": "9. 442 О ФУНКЦИОНИРОВАНИИ РОЗНИЧНЫХ РЫНКОВ.md",
  "category": "legal"
}