{
  "chunk_content": "**57.** Если у энергосбытовой (энергоснабжающей) организации отсутствует или прекратилось право распоряжения электрической энергией (мощностью), поставляемой в точках поставки по договору, обеспечивающему продажу электрической энергии (мощности), то для владельца энергопринимающих устройств, в целях снабжения электрической энергией которых был заключен такой договор, наступают предусмотренные настоящим документом и иными нормативными правовыми актами последствия бездоговорного потребления электрической энергии в определяемом в соответствии с настоящим пунктом объеме потребления, которое не обеспечено продажей по договору с такой энергосбытовой (энергоснабжающей) организацией.\nСетевая организация, к объектам электросетевого хозяйства которой непосредственно или опосредованно присоединены указанные энергопринимающие устройства, в течение 1 дня со дня, когда ей стало известно о факте бездоговорного потребления, направляет владельцу указанных энергопринимающих устройств уведомление, содержащее указание на отсутствие у энергосбытовой (энергоснабжающей) организации права распоряжения электрической энергией в соответствующих точках поставки по договору, с требованием:\n- заключить в соответствии с настоящим документом в течение 30 дней со дня получения уведомления договор, обеспечивающий продажу электрической энергии (мощности);\n- оплатить электрическую энергию (мощность), потребленную указанными энергопринимающими устройствами за весь период, в течение которого осуществлялось бездоговорное потребление электрической энергии.\nПри невыполнении таких требований по истечении 30 дней после дня получения данного уведомления владельцем указанных энергопринимающих устройств сетевая организация принимает меры по сокращению уровня или прекращению потребления электрической энергии указанными энергопринимающими устройствами путем введения полного и (или) частичного ограничения режима потребления электрической энергии в соответствии с пунктом 121 настоящего документа и по обеспечению оплаты владельцем указанных энергопринимающих устройств объема электрической энергии (мощности), потребленной указанными энергопринимающими устройствами за весь период, в течение которого осуществлялось бездоговорное потребление электрической энергии.\nОбъем потребления электрической энергии (мощности) в этом случае рассчитывается в соответствии с разделом X настоящего документа.",
  "breadcrumbs": "Правила функционирования розничных рынков > Статья 57. Последствия бездоговорного потребления",
  "chunk_summary": "Последствия отсутствия права у поставщика распоряжаться энергией, включая статус бездоговорного потребления. Обязанности сетевой организации уведомлять владельца и требовать заключения нового договора в течение 30 дней, а также меры по ограничению потребления.",
  "hypothetical_questions": [
    "Что считается бездоговорным потреблением электроэнергии?",
    "В какие сроки сетевая организация должна уведомить о бездоговорном потреблении?",
    "Сколько времени дается на заключение нового договора после уведомления?",
    "Какие меры применяются при невыполнении требований по бездоговорному потреблению?",
    "Как рассчитывается объем потребления при бездоговорном режиме?"
  ],
  "keywords": [
    "бездоговорное потребление",
    "сетевая организация",
    "уведомление",
    "ограничение режима",
    "30 дней",
    "оплата",
    "договор энергоснабжения",
    "раздел X"
  ],
  "entities": [
    "сетевая организация",
    "владелец энергопринимающих устройств",
    "энергосбытовая организация",
    "пункт 121",
    "раздел X",
    "электрическая энергия"
  ],
  "chunk_id": "a73810630f31_p5",
  "source_file": "9. 442 О ФУНКЦИОНИРОВАНИИ РОЗНИЧНЫХ РЫНКОВ.md",
  "category": "legal"
}