{
  "chunk_content": "## Статья 34. Порядок использования технологической инфраструктуры электроэнергетики субъектами оптового рынка\n1. Взаимодействие субъектов оптового рынка с организацией по управлению единой национальной (общероссийской) электрической сетью, территориальными сетевыми организациями и системным оператором осуществляется в соответствии с устанавливаемыми Правительством Российской Федерации правилами недискриминационного доступа к услугам по передаче электрической энергии, услугам по оперативно-диспетчерскому управлению в электроэнергетике и услугам организаций коммерческой инфраструктуры оптового рынка, правилами технологического функционирования электроэнергетических систем, правилами оперативно-диспетчерского управления в электроэнергетике, а также правилами оптового рынка и иными обязательными требованиями, установленными нормативными правовыми актами Правительства Российской Федерации и уполномоченных им федеральных органов исполнительной власти. Основным принципом использования технологической инфраструктуры электроэнергетики субъектами оптового рынка является обеспечение наиболее эффективной организации экономических отношений на оптовом рынке.\n2. Организация по управлению единой национальной (общероссийской) электрической сетью или системообразующие территориальные сетевые организации оказывают на возмездной договорной основе субъектам оптового рынка услуги по передаче электрической энергии с учетом положений статей 9 и 26 настоящего Федерального закона.\n3. Системный оператор оказывает на возмездной договорной основе субъектам оптового рынка услуги по оперативно-диспетчерскому управлению в электроэнергетике.\n4. Взаимодействие системного оператора и организации по управлению единой национальной (общероссийской) электрической сетью при выполнении ими своих функций осуществляется на основании заключаемого ими безвозмездного соглашения.\n5. Взаимодействие системного оператора и организаций коммерческой инфраструктуры оптового рынка при выполнении ими своих функций осуществляется на основании заключаемого ими безвозмездного соглашения и договора о присоединении к торговой системе оптового рынка.",
  "breadcrumbs": "ФЗ №35 > Статья 34",
  "chunk_summary": "Статья 34 регулирует порядок использования технологической инфраструктуры и взаимодействие с системным оператором и сетевыми организациями.",
  "hypothetical_questions": [
    "Как осуществляется взаимодействие с системным оператором?",
    "Какие услуги оказывают сетевые организации субъектам оптового рынка?",
    "На каком основании заключается соглашение между системным оператором и сетевой организацией?"
  ],
  "keywords": [
    "технологическая инфраструктура",
    "системный оператор",
    "сетевые организации",
    "передача энергии",
    "статья 34",
    "ФЗ №35",
    "оперативно-диспетчерское управление"
  ],
  "category": "ТПП",
  "collection_name": "normative_documents",
  "document_type": "regulation",
  "power_range": "any",
  "client_type": "any",
  "chunk_id": "65feefb6034d_p13",
  "source_file": "1. ФЗ 35 (28.04.2025)"
}