{
  "chunk_content": "**8(3).** (продолжение)\nСетевая организация обязана обеспечить принятие в электронном виде заявок и прилагаемых документов от заявителей (в том числе возможность бесплатного получения заявителями идентификатора и пароля) и возможность получения заявителем сведений об основных этапах обработки заявок юридических и физических лиц и индивидуальных предпринимателей на технологическое присоединение к электрическим сетям, включая информацию о дате поступления заявки и ее регистрационном номере, направлении в адрес заявителей подписанного со стороны сетевой организации договора об осуществлении технологического присоединения к электрическим сетям и технических условий, о дате заключения договора, о ходе выполнения сетевой организацией технических условий, о фактическом присоединении и фактическом приеме (подаче) напряжения и мощности на объекты заявителя, а также о составлении и подписании документов о технологическом присоединении, на своем официальном сайте (в том числе посредством переадресации на официальный сайт, обеспечивающий возможность направлять заявку и прилагаемые документы) или на едином портале (в случае обеспечения сетевой организацией, в которую подается заявка, возможности реализации прав и обязанностей заявителей, возникающих в ходе осуществления процедуры технологического присоединения энергопринимающих устройств к электрическим сетям, с использованием единого портала) в режиме реального времени без использования программного обеспечения, установка которого на технические средства потребителя требует заключения лицензионного или иного соглашения с правообладателем программного обеспечения, предусматривающего взимание с потребителя платы, и без использования специальных аппаратных средств.\n\n(абзац введен Постановлением Правительства РФ от 09.12.2013 N 1131; в ред. Постановлений Правительства РФ от 01.04.2020 N 403, от 14.03.2022 N 360)",
  "breadcrumbs": "Раздел II > Статья 8(3)",
  "chunk_summary": "Пункт 8(3) обязывает сетевую организацию обеспечивать онлайн-отслеживание статуса заявки и обработку документов в электронном виде без дополнительных программ.",
  "hypothetical_questions": [
    "Как отслеживать статус заявки онлайн?",
    "Нужно ли устанавливать специальные программы для подачи заявки?",
    "Бесплатно ли получить доступ к личному кабинету?"
  ],
  "keywords": [
    "отслеживание заявки",
    "статус заявки",
    "реальный режим",
    "бесплатно",
    "личный кабинет",
    "Правила №861"
  ],
  "category": "ТПП",
  "collection_name": "normative_documents",
  "document_type": "regulation",
  "power_range": "any",
  "client_type": "any",
  "chunk_id": "10b7ae460242_p7",
  "source_file": "2. 861 (28.04.2025)"
}