{
  "chunk_content": "---\n\n**27.** При невыполнении заявителем технических условий в согласованный срок и наличии на дату окончания срока их действия технической возможности технологического присоединения сетевая организация по обращению заявителя вправе продлить срок действия ранее выданных технических условий. При этом дополнительная плата не взимается.\n\nПри изменении условий технологического присоединения по окончании срока действия технических условий сетевая организация вправе внести изменения в ранее выданные технические условия или выдать заявителю новые технические условия, учитывающие выполненные по ранее выданным техническим условиям мероприятия. В этом случае выдача новых технических условий не влечет за собой недействительность договора при условии согласования сроков выполнения сторонами мероприятий по технологическому присоединению.\n(в ред. Постановления Правительства РФ от 18.03.2023 N 423)\n\nВыдача новых технических условий в рамках действующего договора заявителям — физическим лицам осуществляется без взимания дополнительной платы.\n\nАбзацы четвертый–восьмой утратили силу с 25 марта 2014 года. — Постановление Правительства РФ от 20.02.2014 N 130.\n\nПродление срока действия ранее выданных технических условий, вносимые в них изменения или выданные заявителю в соответствии с абзацем вторым настоящего пункта новые технические условия подлежат согласованию с системным оператором (в технологически изолированных территориальных электроэнергетических системах до 31 декабря 2023 г. — с субъектом оперативно-диспетчерского управления) в случае, если ранее выданные технические условия были согласованы системным оператором или субъектом оперативно-диспетчерского управления в соответствии с настоящими Правилами.\n(абзац введен Постановлением Правительства РФ от 18.03.2023 N 423)",
  "breadcrumbs": "Правила технологического присоединения > Статья 27",
  "chunk_summary": "Статья 27 описывает порядок продления срока действия технических условий и выдачи новых условий при изменении параметров. Указано, что для физических лиц выдача новых условий в рамках договора бесплатна.",
  "hypothetical_questions": [
    "Как продлить срок действия технических условий?",
    "Сколько стоит продление ТП?",
    "Можно ли изменить ТП после окончания срока?",
    "Бесплатно ли выдаются новые ТП для физлиц?",
    "Нужно ли согласовывать продление с системным оператором?"
  ],
  "keywords": [
    "продление срока",
    "технические условия",
    "изменение условий",
    "дополнительная плата",
    "Постановление №861",
    "системный оператор",
    "физические лица",
    "договор ТП",
    "Правила ТП",
    "сетевая организация"
  ],
  "category": "ТПП",
  "collection_name": "normative_documents",
  "document_type": "regulation",
  "power_range": "any",
  "client_type": "any",
  "chunk_id": "765685319781_p3",
  "source_file": "2. 861 (28.04.2025)"
}