{
  "chunk_content": "## XII. Порядок определения регулируемых цен на электрическую энергию (мощность), поставляемую на розничных рынках на территориях, объединенных в неценовые зоны оптового рынка, за исключением населения и приравненных к нему категорий\n**234.** Исполнительные органы субъектов Российской Федерации в области государственного регулирования тарифов определяют конечные регулируемые цены в соответствии с положениями настоящего раздела.\n\nЗначения конечных регулируемых цен для соответствующей ценовой категории и их составляющих рассчитываются гарантирующими поставщиками (энергосбытовыми, энергоснабжающими организациями) в соответствии с настоящим разделом с точностью до 2 знаков после запятой по правилам математического округления и публикуются гарантирующими поставщиками (энергосбытовыми, энергоснабжающими организациями) на своих официальных сайтах в сети «Интернет» в сроки, указанные в разделе VII настоящего документа, по форме, предусмотренной приложением N 2(1) к настоящему документу.",
  "breadcrumbs": "Раздел XII > Пункт 234",
  "chunk_summary": "Пункт 234 устанавливает общие правила определения конечных регулируемых цен на электрическую энергию для неценовых зон оптового рынка. Исполнительные органы субъектов определяют цены, а гарантирующие поставщики рассчитывают и публикуют их на своих сайтах с точностью до 2 знаков.",
  "hypothetical_questions": [
    "Кто определяет конечные регулируемые цены на электроэнергию в Башкирии?",
    "Где гарантирующий поставщик должен опубликовать тарифы?",
    "С какой точностью рассчитываются конечные регулируемые цены?"
  ],
  "keywords": [
    "конечные регулируемые цены",
    "неценовые зоны",
    "гарантирующий поставщик",
    "пункт 234",
    "Башкирэнерго",
    "оптовый рынок",
    "публикация тарифов"
  ],
  "category": "ТПП",
  "collection_name": "normative_documents",
  "document_type": "regulation",
  "power_range": "any",
  "client_type": "any",
  "chunk_id": "4a37f5471201_p1",
  "source_file": "9. 442 О ФУНКЦИОНИРОВАНИИ РОЗНИЧНЫХ РЫНКОВ"
}