{
  "chunk_content": "1 **Справочно:** Постановлением Государственного комитета Республики Башкортостан по тарифам от 29.11.2024г. № 508 ранее были установлены льготные ставки за 1 кВт запрашиваемой мощности в следующем размере:\n\n1) 6000 руб. за кВт (с учетом НДС) с 1 января 2025 по 31 декабря 2025 года;\n2) 1198,77 руб. за кВт (с учетом НДС) с 1 января 2025 года по 31 декабря 2025 года для некоторых социальных категорий граждан (при предъявлении соответствующих документов, подтверждающих льготы).\n\nВ случае технологического присоединения объектов, указанных в абзацах четвертом и пятом пункта 17 «Правил технологического присоединения энергопринимающих устройств потребителей электрической энергии, объектов по производству электрической энергии, а также объектов электросетевого хозяйства, принадлежащих сетевым организациям и иным лицам, к электрическим сетям», утвержденных Постановлением Правительства РФ от 27.12.2004г. №861 (далее – Правила) и отнесенных к третьей категории надежности (по одному источнику электроснабжения), присоединяемых к объектам электросетевого хозяйства сетевой организации на уровне напряжения 0,4 кВ и ниже, при условии, что расстояние от границ участка заявителя до ближайшего объекта электрической сети необходимого заявителю класса напряжения сетевой организации, в которую подана заявка, составляет не более 300 метров в городах и поселках городского типа и не более 500 метров в сельской местности, плата за технологическое присоединение определяется в **размере минимального из следующих значений**:\n\n- стоимость мероприятий по технологическому присоединению, рассчитанная с применением стандартизированных тарифных ставок;\n- стоимость мероприятий по технологическому присоединению, рассчитанная с применением льготной ставки за 1 кВт запрашиваемой максимальной мощности, которая утверждается в отношении всей совокупности таких мероприятий уполномоченным органом исполнительной власти субъекта Российской Федерации в области государственного регулирования тарифов для соответствующих случаев технологического присоединения в размере не более 10000 рублей за кВт (превышение указанного значения допускается по согласованию с федеральным органом исполнительной власти в области государственного регулирования тарифов) и не менее 3000 рублей за кВт - с 1 июля 2022 г., 4000 рублей за кВт - с 1 июля 2023 г. и 5000 рублей за кВт - с 1 июля 2024 г.",
  "breadcrumbs": "Паспорт услуги > Размер платы > Инвестиционная составляющая",
  "chunk_summary": "Справочная информация о тарифах 2025 года. Описан порядок расчета платы при присоединении к 0,4 кВ на расстоянии до 300/500 метров. Указаны минимальные ставки за кВт.",
  "hypothetical_questions": [
    "Какие тарифы действовали в 2025 году?",
    "Как рассчитывается плата при расстоянии до 300 метров?",
    "Какая минимальная ставка за кВт для ТП?"
  ],
  "keywords": [
    "Постановление № 508",
    "2025 год",
    "6000 руб.",
    "Правила №861",
    "0,4 кВ",
    "300 метров",
    "500 метров",
    "минимальная ставка"
  ],
  "category": "ТПП",
  "collection_name": "normative_documents",
  "document_type": "regulation",
  "power_range": "15-150kW",
  "client_type": "any",
  "chunk_id": "7205d3435ba8_p4",
  "source_file": "passport-tp-15-150kvt"
}